{"updatedAt":"2019-08-08T06:13:58.000Z","facebookLiveChannels":[{"id":80,"facebookVideoUrl":"https://www.facebook.com/standnewshk/videos/373692213343213/","order":1,"channelName":"第二次民間記者會","updatedAt":"2019-08-08T06:13:58.000Z"},{"id":79,"facebookVideoUrl":"https://www.facebook.com/standnewshk/videos/696581964114268/","order":21,"channelName":"校長錢大康晚上 11 時再與學生對話（Part 2）","updatedAt":"2019-08-08T06:13:58.000Z"},{"id":78,"facebookVideoUrl":"https://www.facebook.com/standnewshk/videos/361300374792112/?notif_id=1565189991431145&notif_t=live_video_explicit","order":22,"channelName":"浸大現場 錢大康晚上 11 時對話","updatedAt":"2019-08-08T06:13:58.000Z"},{"id":77,"facebookVideoUrl":"https://www.facebook.com/standnewshk/videos/357624185156006/?notif_id=1565015426815075&notif_t=live_video_explicit","order":23,"channelName":"尖沙咀太空館外","updatedAt":"2019-08-08T06:13:58.000Z"},{"id":76,"facebookVideoUrl":"https://www.facebook.com/standnewshk/videos/342450183366291/","order":24,"channelName":"浸大集會","updatedAt":"2019-08-08T06:13:58.000Z"},{"id":75,"facebookVideoUrl":"https://www.facebook.com/standnewshk/videos/2891757970896228/","order":25,"channelName":"警方每日 4 時例行記者會（Part 2）","updatedAt":"2019-08-08T06:13:58.000Z"},{"id":72,"facebookVideoUrl":"https://www.facebook.com/standnewshk/videos/2336964479904600/","order":26,"channelName":"警方每日 4 時例行記者會（Part 1）","updatedAt":"2019-08-08T06:13:58.000Z"}],"latestNews":[]}