{"updatedAt":"2019-09-11T12:29:00.000Z","facebookLiveChannels":[{"id":546,"facebookVideoUrl":"https://www.facebook.com/standnewshk/videos/509351179827903/","order":1,"channelName":"淘大商場．直播 1","updatedAt":"2019-09-11T12:29:00.000Z"},{"id":545,"facebookVideoUrl":"https://www.facebook.com/standnewshk/videos/378668106147138/","order":11,"channelName":"黃大仙現場．直播 2","updatedAt":"2019-09-11T12:29:00.000Z"},{"id":544,"facebookVideoUrl":"https://www.facebook.com/standnewshk/videos/2927814407234701/","order":51,"channelName":"毛孟靜有關消防 8.31 晚於太子站的行動紀錄內部文件記者會","updatedAt":"2019-09-11T12:29:00.000Z"}],"latestNews":[]}