{"updatedAt":"2020-09-06T06:28:44.000Z","facebookLiveChannels":[{"id":1758,"facebookVideoUrl":"https://www.facebook.com/watch/live/?v=356605215727515&ref=watch_permalink","order":1,"channelName":"九龍大遊行 直播【1】","updatedAt":"2020-09-06T06:28:44.000Z"},{"id":1759,"facebookVideoUrl":"https://www.facebook.com/watch/live/?v=614871742528492&ref=watch_permalink","order":2,"channelName":"九龍大遊行 直播【2】","updatedAt":"2020-09-06T06:28:44.000Z"},{"id":1760,"facebookVideoUrl":"https://www.facebook.com/watch/live/?v=236836031031959&ref=watch_permalink","order":3,"channelName":"九龍大遊行 直播【3】","updatedAt":"2020-09-06T06:28:44.000Z"}],"latestNews":[]}